AUTHORS.rst
CHANGELOG.rst
LICENSE
MANIFEST.in
README.rst
setup.py
jmbo_sitemap/__init__.py
jmbo_sitemap/admin.py
jmbo_sitemap/models.py
jmbo_sitemap/urls.py
jmbo_sitemap/views.py
jmbo_sitemap.egg-info/PKG-INFO
jmbo_sitemap.egg-info/SOURCES.txt
jmbo_sitemap.egg-info/dependency_links.txt
jmbo_sitemap.egg-info/not-zip-safe
jmbo_sitemap.egg-info/requires.txt
jmbo_sitemap.egg-info/top_level.txt
jmbo_sitemap/migrations/0001_initial.py
jmbo_sitemap/migrations/__init__.py
jmbo_sitemap/templates/admin/jmbo_sitemap/htmlsitemap/change_form.html
jmbo_sitemap/templates/jmbo_sitemap/sitemap.html
jmbo_sitemap/tests/__init__.py