Metadata-Version: 1.1
Name: jmbo-sitemap
Version: 2.0.1
Summary: XML and HTML sitemap product for Jmbo
Home-page: http://github.com/praekelt/jmbo-sitemap
Author: Praekelt Foundation
Author-email: dev@praekelt.com
License: BSD
Platform: UNKNOWN
Classifier: Programming Language :: Python
Classifier: License :: OSI Approved :: BSD License
Classifier: Development Status :: 4 - Beta
Classifier: Operating System :: OS Independent
Classifier: Framework :: Django
Classifier: Intended Audience :: Developers
Classifier: Topic :: Internet :: WWW/HTTP :: Dynamic Content
